<?xml version="1.0" encoding="utf-8"?>
<Level mapname="The One Map" maptype="Single Player" maxplayers="2" battleBG="" musictrack="City of the Empire" winAura="0" winMorale="0" lossMorale="0" nextbattle="" defeatScene="" saveable="true" procgen="false" campaign="Actual Lizard Tactics Jam Map for Pride" lastEdited="5/12/2025 4:20:40 PM">

	<Army num="0" AI="false" aiProfile="Custom" name="Army 1" color="Blue" alliedWith="" assignRoster="-1"></Army>
	<Army num="1" AI="true" aiProfile="Aggressive" name="Army 2" color="Red" alliedWith="" assignRoster="-1"></Army>
	
	<Condition>Defeat Army,0,1</Condition>
	
	<Objective>Reclaim the theater and cast out all enemies!</Objective>
	
	<Tileset>01,Wood</Tileset>
	<Tileset>02,Cave</Tileset>
	<Tileset>03,Street</Tileset>
	<Tileset>04,Dirt</Tileset>
	<Tileset>05,Grass</Tileset>
	<Tileset>06,Water</Tileset>
	
	<Row>01.01,01.01,01.0Q,02.01,02.01,02.01,02.3A,02.3J,02.01,02.01,01.0P,01.01,01.01,01.01,01.01,01.01,03.01</Row>
	<Row>01.01,01.01,01.0Q,02.01,02.01,02.01,02.3A,02.3J,01.0R,01.0R,01.0Y,01.01,01.01,01.01,01.01,01.01,03.01</Row>
	<Row>01.01,01.01,01.0Z,01.0R,01.0R,01.01,01.01,01.01,01.01,01.01,01.01,01.01,01.01,01.01,01.01,01.01,03.01</Row>
	<Row>01.01,01.01,01.01,01.01,01.01,01.01,01.01,01.01,01.01,01.01,01.01,01.01,01.01,01.01,01.01,01.01,03.01</Row>
	<Row>01.01,01.01,01.01,01.01,01.01,01.01,01.01,01.01,01.01,01.01,01.01,01.01,01.01,01.01,01.01,01.01,03.01</Row>
	<Row>01.01,01.01,01.01,01.01,01.01,01.01,01.01,01.01,01.01,01.01,01.01,01.01,01.01,01.01,01.01,01.01,03.01</Row>
	<Row>01.01,01.01,01.01,01.01,01.01,01.01,01.01,01.01,01.01,01.01,01.01,01.01,01.01,01.01,01.01,01.01,03.01</Row>
	<Row>01.01,01.01,01.01,01.01,01.01,01.01,01.01,01.01,01.01,01.01,01.01,01.01,01.01,01.01,01.01,01.01,03.01</Row>
	<Row>01.01,01.01,03.01,03.01,01.01,01.01,03.01,03.01,03.01,03.01,03.01,03.01,03.01,03.01,03.01,03.01,03.01</Row>
	<Row>04.2Q,05.01,03.0n,03.01,05.3F,05.3Q,01.01,01.01,01.01,01.01,01.01,01.01,03.01,03.07,03.1K,03.1K,03.1K</Row>
	<Row>04.02,04.06,03.0w,03.0o,05.01,05.2P,01.0f,01.01,01.01,01.01,01.01,01.01,03.01,03.1L,03.01,03.01,03.01</Row>
	<Row>04.2O,04.08,03.1h,03.0o,05.01,05.2P,01.0i,01.0m,01.01,01.01,01.01,01.01,03.01,03.09,03.1J,03.05,03.0u</Row>
	<Row>06.01,06.01,01.01,01.01,05.0K,05.2P,05.01,01.0f,01.01,01.01,01.01,01.01,03.01,05.01,05.01,05.2P,05.07</Row>
	<Row>06.01,06.01,01.01,01.01,06.01,05.09,05.2O,03.1J,03.1J,03.1J,03.1J,03.1J,03.1J,05.2O,05.05,05.09,05.2P</Row>
	<Row>06.01,06.01,01.01,01.01,06.01,05.0O,05.0K,05.0K,05.0P,06.01,06.01,05.0L,05.01,05.01,05.2P,05.01,05.2P</Row>
	<Row>06.01,06.01,01.01,01.01,06.01,06.01,06.01,06.01,06.01,06.01,06.01,05.0L,04.0g,04.0d,05.2P,05.01,05.2P</Row>
	<Row>06.01,06.01,03.1a,03.1k,03.1c,04.0N,04.0N,03.07,03.1K,03.1K,03.1K,03.1K,03.1K,03.1K,05.03,05.01,05.2P</Row>
	<Row>03.1c,03.1c,03.1j,03.07,03.1K,03.1K,03.1K,03.03,03.0k,03.01,03.01,03.01,03.01,03.0o,05.01,05.07,05.03</Row>
	<Row>03.0m,03.0m,03.0u,03.1L,03.01,03.01,03.01,03.01,03.0v,03.0m,03.0m,03.0u,03.01,03.0o,05.01,05.2P,05.01</Row>
	<Row>05.01,05.01,05.07,03.03,03.0u,03.01,03.01,03.0v,03.0r,05.01,05.01,03.0n,03.01,03.0x,05.07,05.03,05.01</Row>
	<Row>05.01,05.01,05.2P,05.01,03.0n,03.01,03.01,03.0o,05.01,05.01,05.01,03.0n,03.01,03.01,05.2P,05.01,05.01</Row>
	
	<RowElev>1,1,1,1,1,1,2,3,2,2,2,2,2,2,2,2,2</RowElev>
	<RowElev>1,1,1,1,1,1,2,3,2,2,2,2,2,2,2,2,2</RowElev>
	<RowElev>1,1,1,1,1,3,3,3,2,2,2,2,2,2,2,2,2</RowElev>
	<RowElev>1,1,1,1,1,3,3,3,2,2,2,2,2,2,2,2,2</RowElev>
	<RowElev>1,1,1,1,1,3,3,3,2,2,2,2,2,2,2,2,2</RowElev>
	<RowElev>1,1,1,1,1,3,3,3,2,2,2,2,2,2,2,2,2</RowElev>
	<RowElev>1,1,1,1,1,3,3,3,2,2,2,2,2,2,2,2,2</RowElev>
	<RowElev>1,1,1,1,1,3,3,3,2,2,2,2,2,2,2,2,2</RowElev>
	<RowElev>2,2,1,1,1,2,2,2,2,2,2,2,2,2,2,2,2</RowElev>
	<RowElev>2,1,1,1,2,2,2,2,2,2,2,2,2,3,3,3,3</RowElev>
	<RowElev>2,2,1,1,1,2,2,2,2,2,2,2,2,3,3,3,3</RowElev>
	<RowElev>2,2,1,1,1,2,2,2,2,2,2,2,2,3,3,3,3</RowElev>
	<RowElev>0,0,2,2,1,2,2,2,2,2,2,2,2,2,2,3,4</RowElev>
	<RowElev>0,0,2,2,0,2,2,2,2,2,2,2,2,2,2,3,4</RowElev>
	<RowElev>0,0,2,2,0,1,1,1,1,0,0,1,1,1,2,2,4</RowElev>
	<RowElev>0,0,2,2,0,0,0,0,0,0,0,1,1,1,2,2,4</RowElev>
	<RowElev>0,0,1,1,1,1,1,2,2,2,2,2,2,2,2,2,4</RowElev>
	<RowElev>1,1,1,2,2,2,2,2,2,2,2,2,2,2,2,4,4</RowElev>
	<RowElev>1,1,1,2,2,2,2,2,2,2,2,2,2,2,2,4,4</RowElev>
	<RowElev>1,1,2,2,2,2,2,2,2,2,2,2,2,2,4,4,4</RowElev>
	<RowElev>1,1,2,2,2,2,2,2,2,2,2,2,2,2,4,4,4</RowElev>
	
	<Unit>0,99,BookcaseFull,0,1,None,None</Unit>
	<Unit>0,99,BookcaseFull,0,2,None,None</Unit>
	<Unit>0,99,HouseWallVertical,0,4,None,None</Unit>
	<Unit>0,99,Chair,0,11,None,None</Unit>
	<Unit>0,99,Chair,0,13,None,None</Unit>
	<Unit>0,99,HouseWallVertical,0,16,None,None</Unit>
	<Unit>0,99,DoorWoodVertical,1,4,None,None</Unit>
	<Unit>0,99,RugTurq9C,1,8,None,None</Unit>
	<Unit>0,99,RugTurq9R,1,9,None,None</Unit>
	<Unit>0,99,HouseWallVertical,1,16,None,None</Unit>
	<Unit>0,99,ClothingBin,2,0,None,None</Unit>
	<Unit>0,99,HouseWallVertical,2,4,None,None</Unit>
	<Unit>0,99,Rug9TL,2,5,None,None</Unit>
	<Unit>0,99,Rug9T,2,6,None,None</Unit>
	<Unit>0,99,Rug9TR,2,7,None,None</Unit>
	<Unit>0,99,RugTurq9C,2,8,None,None</Unit>
	<Unit>0,99,RugTurq9R,2,9,None,None</Unit>
	<Unit>0,99,Chair,2,11,None,None</Unit>
	<Unit>0,99,Chair,2,13,None,None</Unit>
	<Unit>0,99,HouseWallVertical,2,16,None,None</Unit>
	<Unit>0,99,ClothingBin,3,0,None,None</Unit>
	<Unit>0,99,HouseWallVertical,3,4,None,None</Unit>
	<Unit>0,99,Rug9L,3,5,None,None</Unit>
	<Unit>0,99,Rug9C,3,6,None,None</Unit>
	<Unit>0,99,Rug9R,3,7,None,None</Unit>
	<Unit>0,99,RugTurq9C,3,8,None,None</Unit>
	<Unit>0,99,RugTurq9TipTR,3,9,None,None</Unit>
	<Unit>0,99,RugTurq9T,3,10,None,None</Unit>
	<Unit>0,99,RugTurq9T,3,11,None,None</Unit>
	<Unit>0,99,RugTurq9T,3,12,None,None</Unit>
	<Unit>0,99,RugTurq9T,3,13,None,None</Unit>
	<Unit>0,99,RugTurq9T,3,14,None,None</Unit>
	<Unit>0,99,RugTurq9T,3,15,None,None</Unit>
	<Unit>0,99,RugTurq9T,3,16,None,None</Unit>
	<Unit>0,99,HouseWallVertical,4,4,None,None</Unit>
	<Unit>0,99,Rug9L,4,5,None,None</Unit>
	<Unit>0,99,Rug9C,4,6,None,None</Unit>
	<Unit>0,99,Rug9R,4,7,None,None</Unit>
	<Unit>0,99,RugTurq9C,4,8,None,None</Unit>
	<Unit>0,99,RugTurq9TipBR,4,9,None,None</Unit>
	<Unit>0,99,RugTurq9B,4,10,None,None</Unit>
	<Unit>0,99,RugTurq9B,4,11,None,None</Unit>
	<Unit>0,99,RugTurq9B,4,12,None,None</Unit>
	<Unit>0,99,RugTurq9B,4,13,None,None</Unit>
	<Unit>0,99,RugTurq9B,4,14,None,None</Unit>
	<Unit>0,99,RugTurq9B,4,15,None,None</Unit>
	<Unit>0,99,RugTurq9B,4,16,None,None</Unit>
	<Unit>0,99,ClothingBin,5,3,None,None</Unit>
	<Unit>0,99,HouseWallVertical,5,4,None,None</Unit>
	<Unit>0,99,Rug9L,5,5,None,None</Unit>
	<Unit>0,99,Rug9C,5,6,None,None</Unit>
	<Unit>0,99,Rug9R,5,7,None,None</Unit>
	<Unit>0,99,RugTurq9C,5,8,None,None</Unit>
	<Unit>0,99,RugTurq9R,5,9,None,None</Unit>
	<Unit>0,99,Chair,5,11,None,None</Unit>
	<Unit>0,99,HouseWallVertical,5,16,None,None</Unit>
	<Unit>0,99,ClothingBin,6,0,None,None</Unit>
	<Unit>0,99,HouseWallVertical,6,4,None,None</Unit>
	<Unit>0,99,Rug9L,6,5,None,None</Unit>
	<Unit>0,99,Rug9C,6,6,None,None</Unit>
	<Unit>0,99,Rug9R,6,7,None,None</Unit>
	<Unit>0,99,RugTurq9C,6,8,None,None</Unit>
	<Unit>0,99,RugTurq9R,6,9,None,None</Unit>
	<Unit>0,99,HouseWallVertical,6,16,None,None</Unit>
	<Unit>0,99,ClothingBin,7,0,None,None</Unit>
	<Unit>0,99,RackSparse,7,3,None,None</Unit>
	<Unit>0,99,HouseWallVertical,7,4,None,None</Unit>
	<Unit>0,99,Rug9BL,7,5,None,None</Unit>
	<Unit>0,99,Rug9B,7,6,None,None</Unit>
	<Unit>0,99,Rug9BR,7,7,None,None</Unit>
	<Unit>0,99,RugTurq9C,7,8,None,None</Unit>
	<Unit>0,99,RugTurq9R,7,9,None,None</Unit>
	<Unit>0,99,Chair,7,11,None,None</Unit>
	<Unit>0,99,HouseWallVertical,7,16,None,None</Unit>
	<Unit>0,99,HouseWallHorizontal,8,0,None,None</Unit>
	<Unit>0,99,HouseWallHorizontal,8,1,None,None</Unit>
	<Unit tag="Open">0,99,DoorWood,8,2,None,None</Unit>
	<Unit>0,99,HouseWallHorizontal,8,3,None,None</Unit>
	<Unit>0,99,HouseWallT_S,8,4,None,None</Unit>
	<Unit>0,99,HouseWallHorizontal,8,5,None,None</Unit>
	<Unit>0,99,HouseWallT_N,8,6,None,None</Unit>
	<Unit>0,99,HouseWallHorizontal,8,7,None,None</Unit>
	<Unit>0,99,HouseWallHorizontal,8,8,None,None</Unit>
	<Unit>0,99,DoorWood,8,9,None,None</Unit>
	<Unit>0,99,HouseWallHorizontal,8,10,None,None</Unit>
	<Unit>0,99,HouseWallHorizontal,8,11,None,None</Unit>
	<Unit>0,99,HouseWallT_N,8,12,None,None</Unit>
	<Unit>0,99,HouseWallHorizontal,8,13,None,None</Unit>
	<Unit>0,99,HouseWallHorizontal,8,14,None,None</Unit>
	<Unit>0,99,HouseWallHorizontal,8,15,None,None</Unit>
	<Unit>0,99,HouseWallSE,8,16,None,None</Unit>
	<Unit>0,99,Bush,9,1,None,None</Unit>
	<Unit>0,99,PlanterLilies,9,5,None,None</Unit>
	<Unit>0,99,HouseWallVertical,9,6,None,None</Unit>
	<Unit>0,99,BookcaseFull,9,7,None,None</Unit>
	<Unit>0,99,RackSparse,9,11,None,None</Unit>
	<Unit>0,99,HouseWallVertical,9,12,None,None</Unit>
	<Unit>0,99,Barrel,9,13,None,None</Unit>
	<Unit>0,99,Chair,9,14,None,None</Unit>
	<Unit>0,99,Barrel,10,0,None,None</Unit>
	<Unit>0,99,HouseWallVertical,10,6,None,None</Unit>
	<Unit>0,99,TableBeer,10,8,None,None</Unit>
	<Unit>0,99,DoorWoodVertical,10,12,None,None</Unit>
	<Unit>0,99,TableFood,10,14,None,None</Unit>
	<Unit>0,99,FruitStandStriped_E,11,0,None,None</Unit>
	<Unit>0,99,HouseWallSW,11,6,None,None</Unit>
	<Unit>0,99,HouseWallNE,11,7,None,None</Unit>
	<Unit>0,99,HouseWallVertical,11,12,None,None</Unit>
	<Unit>0,99,HouseWallVertical,12,7,None,None</Unit>
	<Unit>0,99,HouseWallVertical,12,12,None,None</Unit>
	<Unit>0,99,Bush,12,13,None,None</Unit>
	<Unit>0,99,Tree,12,16,None,None</Unit>
	<Unit>0,99,ReedsFlower,13,6,None,None</Unit>
	<Unit>0,99,HouseWallSW,13,7,None,None</Unit>
	<Unit>0,99,HouseWallHorizontal,13,8,None,None</Unit>
	<Unit>0,99,HouseWallHorizontal,13,9,None,None</Unit>
	<Unit>0,99,HouseWallHorizontal,13,10,None,None</Unit>
	<Unit>0,99,HouseWallHorizontal,13,11,None,None</Unit>
	<Unit>0,99,HouseWallSE,13,12,None,None</Unit>
	<Unit>0,99,Wildflowers,13,15,None,None</Unit>
	<Unit>0,99,Barrel,14,3,None,None</Unit>
	<Unit>0,99,ReedsFlowerSmall,14,12,None,None</Unit>
	<Unit>0,99,WildflowersAlt,14,14,None,None</Unit>
	<Unit>0,99,Bush,15,14,None,None</Unit>
	<Unit>0,99,ReedsSmall,16,6,None,None</Unit>
	<Unit>0,99,Wildflowers,16,16,None,None</Unit>
	<Unit>0,99,Birdbath,17,15,None,None</Unit>
	<Unit>0,99,Reeds,18,14,None,None</Unit>
	<Unit>0,99,Caravan_E,19,0,None,None</Unit>
	<Unit>0,99,Reeds,19,9,None,None</Unit>
	<Unit>0,99,Evergreen,19,10,None,None</Unit>
	<Unit>0,99,Wildflowers,19,14,None,None</Unit>
	<Unit>0,99,Bush,20,3,None,None</Unit>
	<Unit>0,99,WildflowersAlt,20,8,None,None</Unit>
	<Unit>0,99,TreeFruit,20,9,None,Apple/Apple/Apple</Unit>
	<Unit>0,0,Arora/,16,12,Up,None</Unit>
	<Unit>0,0,Drasan/Winterbloom,17,11,Left,None</Unit>
	<Unit>0,0,Nobeta/,17,13,Left,None</Unit>
	<Unit>0,0,Harrien/,18,10,Left,None</Unit>
	<Unit>0,0,Kyat/,19,13,Left,None</Unit>
	<Unit>0,1,Rubble Rouser Golem/,0,12,Up,None</Unit>
	<Unit tag="Passive/Add,LevelUp,4">0,1,Rabble Rouser Crossbowjock/,2,1,Down,None</Unit>
	<Unit tag="Passive/Add,LevelUp,4">0,1,Rubble Rouser Bruiser/,3,6,Down,None</Unit>
	<Unit tag="Passive/Add,LevelUp,4">0,1,Rabble Rouser Crossbowjock/,3,11,Left,None</Unit>
	<Unit tag="Passive">0,1,Clark/,4,3,Left,None</Unit>
	<Unit>0,1,Rubble Rouser Golem/,6,3,Left,None</Unit>
	<Unit tag="Passive/Add,LevelUp,4">0,1,Rubble Rouser Bruiser/,6,6,Up,None</Unit>
	<Unit>0,1,Rubble Rouser Golem/,7,1,Up,None</Unit>
	<Unit tag="Passive">0,1,Rubble Rouser Golem/,7,15,Right,None</Unit>
	<Unit tag="Passive/Add,LevelUp,4">0,1,Rubble Rouser Bruiser/,9,8,Down,None</Unit>
	<Unit tag="Add,LevelUp,4">0,1,Rubble Rouser Bruiser/,10,15,Left,None</Unit>
	<Unit tag="Passive/Add,LevelUp,4">0,1,Rabble Rouser Crossbowjock/,11,8,Up,None</Unit>
	<Unit>0,1,Rubble Rouser Golem/,13,2,Down,None</Unit>
	<Unit>0,1,Rubble Rouser Golem/,13,14,Down,None</Unit>
	<Unit>0,1,Rubble Rouser Golem/,16,9,Right,None</Unit>
	<Unit tag="Add,LevelUp,4">0,1,Rubble Rouser Bruiser/,18,0,Down,None</Unit>
	<Unit>0,1,Rubble Rouser Golem/,18,3,Right,None</Unit>
	<Unit tag="Add,LevelUp,4">0,1,Rubble Rouser Bruiser/,18,6,Right,None</Unit>

	<Script>Set Lesbian Talkable
		<Action>AddStatus/Kyat,Talkable</Action>
		<Action>AddStatus/Nobeta,Talkable</Action>
		<Action>SetString/Nobeta Can Talk,Nobeta</Action>
	</Script>

	<Script>Set Lesbian Not Talkable
		<Action>RemoveStatus/Kyat,Talkable</Action>
		<Action>RemoveStatus/Nobeta,Talkable</Action>
		<Action>SetString/Nobeta Can Talk,INVALID</Action>
	</Script>

	<Script>Asandr Progresses Script
		<Action>SetVal/Asandr Name Progress,+:1</Action>
		<Action>IfValRun/Asandr Name Progress,=,4,Swap Out Unit,Swap Out Name,Sandra Winterbloom,Swap In Name,Asandr Winterbloom</Action>
		<Action>IfValRun/Asandr Name Progress,=,3,Swap Out Unit,Swap Out Name,Rasand Winterbloom,Swap In Name,Sandra Winterbloom</Action>
		<Action>IfValRun/Asandr Name Progress,=,2,Swap Out Unit,Swap Out Name,Rasand Winterbloom,Swap In Name,Andras Winterbloom</Action>
		<Action>IfValRun/Asandr Name Progress,=,1,Swap Out Unit,Swap Out Name,Drasan Winterbloom,Swap In Name,Andras Winterbloom</Action>
	</Script>

	<Script>Swap Out Unit
		<Action>Run/Store Character Stats,Prefix,SwapOut,Character Name,-STR:Swap Out Name-</Action>
		<Action>RemoveUnit/-STR:Swap Out Name-,false</Action>
		<Action>SpawnUnit/0,-STR:Swap In Name-,-VAL:SwapOutY Coord-,-VAL:SwapOutX Coord-,-VAL:SwapOutFacing-,,,-STR:SwapOutInventoryString-,false</Action>
		<Action>Run/Load Character Stats,Character Name,-STR:Swap In Name-,Prefix,SwapOut</Action>
		<Action>SpawnUnit/Army Number,Load ID (using : in lieu of /),Y coordinate,X coordinate,Facing (Up Down Left Right),Triggers (using : in lieu of , and :: in lieu of / -- optional),Tags (using : in lieu of , and :: in lieu of / -- optional),Inventory (delimit items with : -- optional),Drop Into Place (true or false -- optional)</Action>
	</Script>

	<Script>Store Character Stats
		<Action>SetList/Variables To List,Accuracy|Dodge|Counter Limit|Experience|Level|Morale|Perception|Psy|Reflexes|Slash Res.|Pierce Res.|Crush Res.|Mental Res.|Heat Res.|Cold Res.|Shadow Res.|Light Res.|Poison Res.|Speed|Strength|Health|Salary|Facing|X Coord|Y Coord|Drain|Damage</Action>
		<Action>InvToList/-STR:Character Name-,-STR:Prefix-Inventory-STR:Suffix-</Action>
		<Action>ListToString/-STR:Prefix-Inventory-STR:Suffix-,:,-STR:Prefix-InventoryString-STR:Suffix-</Action>
		<Action>ForLoop/-ii-,0-LASTINLIST[Variables To List],1,SetValByStat,-STR:Prefix-LIST{Variables To List,-ii-}-STR:Suffix-,=,-STR:Swap Out Name-,LIST{Variables To List,-ii-}</Action>
	</Script>

	<Script>Load Character Stats
		<Action>SetList/Variables To List,Accuracy|Dodge|Counter Limit|Experience|Level|Morale|Perception|Psy|Reflexes|Slash Res.|Pierce Res.|Crush Res.|Mental Res.|Heat Res.|Cold Res.|Shadow Res.|Light Res.|Poison Res.|Speed|Strength|Health|Salary|Drain|Damage</Action>
		<Action>ForLoop/-ii-,0-LASTINLIST[Variables To List],1,Run,Load Character Stat Subroutine,Prefix,-STR:Prefix-,Suffix,-STR:Suffix-,Character Name,-STR:Character Name-,Stat,LIST{Variables To List,-ii-}</Action>
	</Script>

	<Script>Load Character Stat Subroutine
		<Action>SetValByVal/NextLoadedStatValue,=,-STR:Prefix--STR:Stat--STR:Suffix-</Action>
		<Action>Log/Load Character Stat Subroutine Testing Log
-VAL:NextLoadedStatValue- -STR:Character Name- -STR:Stat-</Action>
		<Action>SetStatByVal/-STR:Character Name-,-STR:Stat-,=,NextLoadedStatValue</Action>
	</Script>

	<Dialogue trigger="OnTalk/Kyat,-STR:Nobeta Can Talk-" convID="Lesbians Talk Dialogue" r="true">
		<Branch num="0" name="">/
			<Action>Run/Set Lesbian Not Talkable</Action>
			<Action>SetVal/Lesbian Discussions Count,+:1</Action>
			<Action>IfValGoTo/Lesbian Discussions Count,=,1,Go To First Lesbian Dialogue</Action>
			<Action>IfValGoTo/Lesbian Discussions Count,=,2,Go To Second Lesbian Dialogue</Action>
			<Action>IfValGoTo/Lesbian Discussions Count,=,3,Go To Third Lesbian Dialogue</Action>
			<Action>EndConvImmediately/</Action>
		</Branch>
		<Branch num="1" name="Go To First Lesbian Dialogue">/
			<Action>LoadConv/First Lesbian Dialogue</Action>
		</Branch>
		<Branch num="2" name="Go To Second Lesbian Dialogue">/
			<Action>LoadConv/Second Lesbian Dialogue</Action>
		</Branch>
		<Branch num="3" name="Go To Third Lesbian Dialogue">/
			<Action>LoadConv/Third Lesbian Dialogue</Action>
		</Branch>
	</Dialogue>

	<Dialogue trigger="OnTurn/-VAL:Turn Trigger-" convID="Round Start Dialogue" r="true">
		<Branch num="0" name="">/
			<Action>SetVal/Turn Trigger,+:1</Action>
			<Action>IfValRun/Lesbian Discussions Count,l,3,Set Lesbian Talkable</Action>
			<Action>IfValRun/Asandr Name Progress,=,1,SetString,AndrasReadyToShave,Andras Winterbloom</Action>
			<Action>EndConvImmediately/</Action>
			<Action>/</Action>
		</Branch>
	</Dialogue>

	<Dialogue trigger="BeforeTurn/0" convID="Map Start Dialogue" r="false">
		<Branch num="0" name="">/
			<Action>SetVal/Lesbian Discussions Count,=:0</Action>
			<Action>SetVal/Turn Trigger,0</Action>
			<Action>AddTagToArmy/1,Passive</Action>
			<Action>Run/Set Lesbian Talkable</Action>
			<Action>SetVal/Asandr Name Progress,0</Action>
			<Action>SetString/Asandr Current Name,Drasan Winterbloom</Action>
			<Action>SetArea/Clothing Zone,0,8,0,4</Action>
			<Action>SetString/AndrasReadyToShave,INVALID</Action>
			<Action>EndConvImmediately/</Action>
		</Branch>
	</Dialogue>

	<Dialogue trigger="None/" convID="First Lesbian Dialogue" r="false">
		<Branch num="0" name="">Kyat/Wow, this would be a discussion! Our first one, I think.
			<Action>AddPortrait/Kyat,Kyat,left</Action>
			<Action>AddPortrait/Nobeta,Nobeta,right</Action>
			<Action>SetStat/Kyat,Morale,+:2</Action>
			<Action>SetStat/Nobeta,Morale,+:2</Action>
			<Reply>Continue./NextBranch</Reply>
		</Branch>
	</Dialogue>

	<Dialogue trigger="None/" convID="Second Lesbian Dialogue" r="false">
		<Branch num="0" name="">Nobeta/Isn't this our second conversation? Well then.
			<Action>AddPortrait/Kyat,Kyat,left</Action>
			<Action>AddPortrait/Nobeta,Nobeta,right</Action>
			<Action>SetStat/Kyat,Morale,+:2</Action>
			<Action>SetStat/Nobeta,Morale,+:2</Action>
			<Reply>Continue./NextBranch</Reply>
		</Branch>
	</Dialogue>

	<Dialogue trigger="None/" convID="Third Lesbian Dialogue" r="false">
		<Branch num="0" name="">Kyat/This is our third conversation. Well, I guess that's it then.
			<Action>AddPortrait/Kyat,Kyat,left</Action>
			<Action>AddPortrait/Nobeta,Nobeta,right</Action>
			<Action>SetStat/Kyat,Morale,+:2</Action>
			<Action>SetStat/Nobeta,Morale,+:2</Action>
			<Reply>Continue./NextBranch</Reply>
		</Branch>
	</Dialogue>

	<Dialogue trigger="OnTalk/Clark,Harrien" convID="Clark Dialogue" r="false">
		<Branch num="0" name="">Clark/Man, I really don't wanna fight you. I was really hoping someone else would handle you... look at those arms! You could tear me apart!
			<Action>AddPortrait/Clark,Clark,left</Action>
			<Action>AddPortrait/Harrien,Harrien,right</Action>
			<Reply>Continue./NextBranch</Reply>
		</Branch>
		<Branch num="1" name="">Harrien/...Well, that just sucks all the fun out of fighting you. What's someone so meek doing with this lot?
			<Reply>Continue./NextBranch</Reply>
		</Branch>
		<Branch num="2" name="">Clark/I... really don't know. I've been trying to find where it went wrong, but all I can really conclude is that I made very dumb decisions.
			<Reply>Continue./NextBranch</Reply>
		</Branch>
		<Branch num="3" name="">Harrien/Sounds like a lot of us, honestly.  ...Look, I can't undo the stuff you've been dealt, but I can offer you an out. C'mon and join us! If you're on the field, you must have some skill, right?
			<Reply>Continue./NextBranch</Reply>
		</Branch>
		<Branch num="4" name="">Clark/W-w-what? Um, I... no, I'd really just weigh you down.
			<Reply>Continue./NextBranch</Reply>
		</Branch>
		<Branch num="5" name="">Harrien/Hey, c'mon, look at these guns. A little extra weight won't bug me.
			<Reply>Continue./NextBranch</Reply>
		</Branch>
		<Branch num="6" name="">Clark/...W-well, okay. ...Thank you.
			<Action>SetStat/Clark,Army,=:0</Action>
			<Action>RemoveConv/Clark Dialogue</Action>
			<Action>RemoveStatus/Clark,Talkable</Action>
			<Action>RemovePortrait/Clark</Action>
			<Action>AddPortrait/Clark,Clark,left</Action>
			<Action>SetStat/Clark,Morale,=4</Action>
			<Reply>Continue./NextBranch</Reply>
		</Branch>
	</Dialogue>

	<Dialogue trigger="OnReachingArea/Clothing Zone,Drasan Winterbloom" convID="Sandra First Clothes" r="false">
		<Branch num="0" name="">Drasan Winterbloom/Oh, what do we have here? [Drasan sees an open container of clothes for performers] This is...
			<Action>AddPortrait/Drasan Winterbloom,Drasan Winterbloom,left,,Quizzical</Action>
			<Reply>Continue./NextBranch</Reply>
		</Branch>
		<Branch num="1" name="">Drasan Winterbloom/[Drasan nervously grabs an outfit from the chest]
			<Action>AddPortrait/Drasan Winterbloom,Drasan Winterbloom,left,,Concerned</Action>
			<Reply>Continue./NextBranch</Reply>
		</Branch>
		<Branch num="2" name="">Andras Winterbloom/I could... use a change.
			<Action>Run/Asandr Progresses Script</Action>
			<Action>AddPortrait/Andras Winterbloom,Andras Winterbloom,left,,Happy</Action>
			<Action>PortraitParticles/Andras Winterbloom,Heart</Action>
			<Reply>Continue./NextBranch</Reply>
		</Branch>
	</Dialogue>

	<Dialogue trigger="OnCharSelected/0,-STR:AndrasReadyToShave-" convID="Andras Shaves" r="false">
		<Branch num="0" name="">Andras Winterbloom/If I can change anything, then... [Andras carefully presses a sword to their lip]
			<Action>SetString/AndrasReadyToShave,INVALID</Action>
			<Action>AddPortrait/Andras Winterbloom,Andras Winterbloom,left,,Nervous</Action>
			<Reply>Continue./NextBranch</Reply>
		</Branch>
		<Branch num="1" name="">Rasand Winterbloom/...that feels much better.
			<Action>Run/Swap Out Unit,Prefix,Swap Out Name,Andras Winterbloom,Swap In Name,Rasand Winterbloom</Action>
			<Action>AddPortrait/Rasand Winterbloom,Rasand Winterbloom,,Happy</Action>
			<Action>PortraitParticles/Rasand Winterbloom,Heart</Action>
			<Reply>Continue./NextBranch</Reply>
		</Branch>
	</Dialogue>

</Level>